Metadata-Version: 2.1
Name: c8ylp
Version: 2.5.0
Summary: Cumulocity Local Client Proxy
Home-page: https://github.com/SoftwareAG/cumulocity-remote-access-local-proxy
Author: Stefan Witschel
Author-email: Stefan.Witschel@softwareag.com
License: Apache v2
Requires-Python: >=3.7
License-File: LICENSE
Requires-Dist: requests >=2.26.0
Requires-Dist: websocket-client >=1.2.1
Requires-Dist: certifi >=2020.12.5
Requires-Dist: click ==8.1.7
